cachai/__init__.py
cachai/__main__.py
cachai/_core/chord.py
cachai/chplot.py
cachai/data/__init__.py
cachai/data/_utils.py
cachai/data/remote_data.py
cachai/gadgets.py
cachai/tests/__init__.py
cachai/tests/_run_test.py
cachai/tests/conftest.py
cachai/tests/test_charts.py
cachai/tests/test_data.py
cachai/tests/test_dependencies.py
cachai/tests/test_gadgets.py
cachai/tests/test_utilities.py
cachai/utilities.py
cachai-0.1.4.dist-info/METADATA
cachai-0.1.4.dist-info/WHEEL
cachai-0.1.4.dist-info/entry_points.txt
cachai-0.1.4.dist-info/licenses/LICENSE
cachai-0.1.4.dist-info/RECORD
