Metadata-Version: 2.4
Name: cachai
Version: 0.1.4
Summary: Customizable visualization toolkit for science
License: GPL-3.0-or-later
License-File: LICENSE
Author: Diego Beltrán Flores
Author-email: d.beltran@outlook.cl
Maintainer: Diego Beltrán Flores
Maintainer-email: d.beltran@outlook.cl
Requires-Python: >=3.10
Classifier: Framework :: Matplotlib
Classifier: Intended Audience :: Science/Research
Classifier: License :: OSI Approved :: GNU General Public License v3 or later (GPLv3+)
Classifier: Operating System :: OS Independent
Classifier: Programming Language :: Python :: 3
Classifier: Programming Language :: Python :: 3.10
Classifier: Programming Language :: Python :: 3.11
Classifier: Programming Language :: Python :: 3.12
Classifier: Programming Language :: Python :: 3.13
Classifier: Programming Language :: Python :: 3.14
Classifier: Topic :: Scientific/Engineering :: Visualization
Provides-Extra: testing
Requires-Dist: matplotlib (>=3.9.0,!=3.9.1)
Requires-Dist: numpy (>=2.0.0)
Requires-Dist: pandas (>=2.3.0)
Requires-Dist: pytest (>=7.1.0) ; extra == "testing"
Requires-Dist: scipy (>=1.13.0)
Requires-Dist: seaborn (>=0.12.0)
Project-URL: Changelog, https://github.com/DD-Beltran-F/cachai/releases
Project-URL: Documentation, https://cachai.readthedocs.io/en/latest/documentation/indexdoc.html
Project-URL: Homepage, https://cachai.readthedocs.io/en/latest/index.html
Project-URL: Issues, https://github.com/DD-Beltran-F/cachai/issues
Project-URL: Repository, https://github.com/DD-Beltran-F/cachai
Project-URL: Related Publication, https://iopscience.iop.org/article/10.3847/2515-5172/adf8df
